sverigesradio/__init__.py
sverigesradio-0.3.dist-info/DESCRIPTION.rst
sverigesradio-0.3.dist-info/METADATA
sverigesradio-0.3.dist-info/pydist.json
sverigesradio-0.3.dist-info/RECORD
sverigesradio-0.3.dist-info/top_level.txt
sverigesradio-0.3.dist-info/WHEEL
