Metadata-Version: 2.0
Name: sverigesradio
Version: 0.3
Summary: Python bindings for Sveriges Radio API
Home-page: https://github.com/tiwilliam/sverigesradio
Author: William Tisäter
Author-email: william@defunct.cc
License: MIT License
Keywords: sr sverigesradio
Platform: UNKNOWN
Classifier: Programming Language :: Python
Classifier: Programming Language :: Python :: 2.5
Classifier: Programming Language :: Python :: 2.6
Classifier: Programming Language :: Python :: 2.7
Classifier: Programming Language :: Python :: 3
Classifier: Programming Language :: Python :: 3.2
Classifier: Programming Language :: Python :: 3.3
Requires-Dist: requests (>=2.1.0)
